pyunlocode/__init__.py
pyunlocode/init_db.py
pyunlocode/parser.py
pyunlocode/unlocode.db
pyunlocode/csv/2023-1 SubdivisionCodes.csv
pyunlocode/csv/2023-1 UNLOCODE CodeListPart1.csv
pyunlocode/csv/2023-1 UNLOCODE CodeListPart2.csv
pyunlocode/csv/2023-1 UNLOCODE CodeListPart3.csv
pyunlocode-0.1.0.dist-info/LICENSE
pyunlocode-0.1.0.dist-info/METADATA
pyunlocode-0.1.0.dist-info/WHEEL
pyunlocode-0.1.0.dist-info/entry_points.txt
pyunlocode-0.1.0.dist-info/top_level.txt
pyunlocode-0.1.0.dist-info/RECORD
